ThetaSynthesis/__init__.py
ThetaSynthesis/scroll.py
ThetaSynthesis/tree.py
ThetaSynthesis/abc/__init__.py
ThetaSynthesis/abc/scroll.py
ThetaSynthesis/abc/tree.py
ThetaSynthesis/synthon/__init__.py
ThetaSynthesis/synthon/dummy.py
ThetaSynthesis/synthon/greedy.py
ThetaSynthesis/synthon/abc/__init__.py
ThetaSynthesis/synthon/abc/synthon.py
ThetaSynthesis/synthon/policy/__init__.py
ThetaSynthesis/synthon/policy/data/bb.smi
ThetaSynthesis/synthon/policy/data/rules.pickle
ThetaSynthesis/synthon/policy/model/__init__.py
ThetaSynthesis/synthon/policy/model/dataloader.py
ThetaSynthesis/synthon/policy/model/double_headed.py
ThetaSynthesis/synthon/policy/model/oneheaded.py
ThetaSynthesis/synthon/rollout/__init__.py
ThetaSynthesis/synthon/rollout/data/building_blocks.smiles
ThetaSynthesis/synthon/rollout/rules/__init__.py
ThetaSynthesis/synthon/rollout/rules/decompositions.py
ThetaSynthesis/synthon/rollout/rules/transformations.py
ThetaSynthesis-0.1.0.dist-info/METADATA
ThetaSynthesis-0.1.0.dist-info/WHEEL
ThetaSynthesis-0.1.0.dist-info/top_level.txt
ThetaSynthesis-0.1.0.dist-info/zip-safe
ThetaSynthesis-0.1.0.dist-info/RECORD
